banking533/main.py
banking533/admin/__init__.py
banking533/admin/action.py
banking533/admin/card.py
banking533/admin/store.py
banking533/admin/view.py
banking533/user/__init__.py
banking533/user/account.py
banking533/user/transaction.py
Banking533-0.0.1.dist-info/LICENSE.txt
Banking533-0.0.1.dist-info/METADATA
Banking533-0.0.1.dist-info/WHEEL
Banking533-0.0.1.dist-info/top_level.txt
Banking533-0.0.1.dist-info/RECORD
