Metadata-Version: 2.1
Name: Banking533
Version: 0.0.1
Summary: An example package
Author-email: test <test@gmail.com>
Project-URL: Homepage, https://github.com/zhangz128/DATA533-project-step3-group20.git
Project-URL: Issues, https://github.com/zhangz128/DATA533-project-step3-group20.git
Classifier: Programming Language :: Python :: 3
Classifier: License :: OSI Approved :: MIT License
Classifier: Operating System :: OS Independent
Requires-Python: >=3.8
License-File: LICENSE.txt
